effect_ae/__init__.py
effect_ae/action_items.py
effect_ae/admin/__init__.py
effect_ae/admin/ae_followup_admin.py
effect_ae/admin/ae_initial_admin.py
effect_ae/admin/ae_local_review_admin.py
effect_ae/admin/ae_sponsor_review_admin.py
effect_ae/admin/ae_susar_admin.py
effect_ae/admin/ae_tmg_admin.py
effect_ae/admin/death_report_admin.py
effect_ae/admin/death_report_tmg_admin.py
effect_ae/admin/death_report_tmg_second_admin.py
effect_ae/admin/modeladmin_mixins.py
effect_ae/admin_site.py
effect_ae/apps.py
effect_ae/baker_recipes.py
effect_ae/choices.py
effect_ae/form_validators/__init__.py
effect_ae/form_validators/ae_initial.py
effect_ae/forms/__init__.py
effect_ae/forms/ae_followup_form.py
effect_ae/forms/ae_initial_form.py
effect_ae/forms/ae_local_review_form.py
effect_ae/forms/ae_sponsor_review_form.py
effect_ae/forms/ae_susar_form.py
effect_ae/forms/ae_tmg_form.py
effect_ae/forms/death_report_form.py
effect_ae/forms/death_report_tmg_form.py
effect_ae/forms/death_report_tmg_second_form.py
effect_ae/forms/modelform_mixins.py
effect_ae/list_data.py
effect_ae/migrations/0001_initial.py
effect_ae/migrations/0002_auto_20220309_1441.py
effect_ae/migrations/0003_auto_20220322_2029.py
effect_ae/migrations/0004_auto_20220419_2126.py
effect_ae/migrations/0005_auto_20220504_0602.py
effect_ae/migrations/0006_auto_20220516_1203.py
effect_ae/migrations/0007_auto_20220516_1759.py
effect_ae/migrations/0008_auto_20220711_1230.py
effect_ae/migrations/0009_auto_20220824_1919.py
effect_ae/migrations/0010_auto_20220826_1549.py
effect_ae/migrations/0011_auto_20220910_2045.py
effect_ae/migrations/0012_rename_narrative_aetmg_investigator_narrative_and_more.py
effect_ae/migrations/0013_alter_deathreporttmg_cause_of_death_agreed_and_more.py
effect_ae/migrations/0014_delete_superfluous_ae_classifiers.py
effect_ae/migrations/0015_alter_aefollowup_managers_alter_aeinitial_managers_and_more.py
effect_ae/migrations/0016_alter_aefollowup_options_alter_aeinitial_options_and_more.py
effect_edc-1.4.0.dist-info/licenses/LICENSE
effect_edc-1.4.0.dist-info/WHEEL
effect_edc-1.4.0.dist-info/METADATA
effect_edc-1.4.0.dist-info/RECORD
