Metadata-Version: 2.4
Name: effect-edc
Version: 1.4.0
Summary: EFFECT Trial EDC (https://www.isrctn.com/ISRCTN30579828)
Keywords: django,clinicedc,EFFECT EDC,EDC,clinical trials,META Trial,ISRCTN30579828
Author: Erik van Widenfelt, Jonathan Willitts
Author-email: Erik van Widenfelt <ew2789@gmail.com>, Jonathan Willitts <j.willitts@ucl.ac.uk>
License-Expression: GPL-3.0-or-later
License-File: LICENSE
Classifier: Development Status :: 5 - Production/Stable
Classifier: Framework :: Django
Classifier: Framework :: Django :: 5.2
Classifier: Intended Audience :: Developers
Classifier: Intended Audience :: Science/Research
Classifier: Operating System :: OS Independent
Classifier: Programming Language :: Python :: 3.12
Classifier: Programming Language :: Python :: 3.13
Requires-Dist: django==5.2.10
Requires-Dist: beautifulsoup4>=4.13.4
Requires-Dist: clinicedc>=2.4.4
Requires-Dist: effect-form-validators>=1.5.0
Requires-Dist: edc-csf>=1.3.0
Requires-Dist: edc-microbiology>=1.3.0
Requires-Dist: notebook>=7.4.5
Requires-Dist: reportlab>=4.4.4
Requires-Python: >=3.12, <3.14
Project-URL: Homepage, https://github.com/effect-trial/effect-edc
Project-URL: Repository, https://github.com/effect-trial/effect-edc.git
Project-URL: Changelog, https://github.com/effect-trial/effect-edc/blob/main/CHANGELOG
